{"nodes": [{"id": "d_nikke_mda_agent_go_service_taskersink_membership_memberdata_go", "label": "memberdata.go", "file_type": "code", "source_file": "D:\\NIKKE\\MDA\\agent\\go-service\\taskersink\\membership\\memberdata.go", "source_location": "L1"}, {"id": "membership_memberdata_setversion", "label": "SetVersion()", "file_type": "code", "source_file": "D:\\NIKKE\\MDA\\agent\\go-service\\taskersink\\membership\\memberdata.go", "source_location": "L20"}, {"id": "membership_memberdata_isdebugversion", "label": "isDebugVersion()", "file_type": "code", "source_file": "D:\\NIKKE\\MDA\\agent\\go-service\\taskersink\\membership\\memberdata.go", "source_location": "L25"}, {"id": "membership_memberrecord", "label": "MemberRecord", "file_type": "code", "source_file": "D:\\NIKKE\\MDA\\agent\\go-service\\taskersink\\membership\\memberdata.go", "source_location": "L42"}, {"id": "membership_membershipstatus", "label": "MembershipStatus", "file_type": "code", "source_file": "D:\\NIKKE\\MDA\\agent\\go-service\\taskersink\\membership\\memberdata.go", "source_location": "L56"}, {"id": "membership_memberdata_getmembershipstatus", "label": "GetMembershipStatus()", "file_type": "code", "source_file": "D:\\NIKKE\\MDA\\agent\\go-service\\taskersink\\membership\\memberdata.go", "source_location": "L83"}, {"id": "membership_memberdata_checkmembership", "label": "checkMembership()", "file_type": "code", "source_file": "D:\\NIKKE\\MDA\\agent\\go-service\\taskersink\\membership\\memberdata.go", "source_location": "L96"}, {"id": "membership_memberdata_fetchmemberdata", "label": "fetchMemberData()", "file_type": "code", "source_file": "D:\\NIKKE\\MDA\\agent\\go-service\\taskersink\\membership\\memberdata.go", "source_location": "L168"}, {"id": "membership_memberdata_fetchfromsource", "label": "fetchFromSource()", "file_type": "code", "source_file": "D:\\NIKKE\\MDA\\agent\\go-service\\taskersink\\membership\\memberdata.go", "source_location": "L193"}, {"id": "membership_memberdata_matchdevicecode", "label": "matchDeviceCode()", "file_type": "code", "source_file": "D:\\NIKKE\\MDA\\agent\\go-service\\taskersink\\membership\\memberdata.go", "source_location": "L223"}, {"id": "membership_memberdata_calculatestatus", "label": "calculateStatus()", "file_type": "code", "source_file": "D:\\NIKKE\\MDA\\agent\\go-service\\taskersink\\membership\\memberdata.go", "source_location": "L250"}, {"id": "membership_memberdata_dayssince", "label": "daysSince()", "file_type": "code", "source_file": "D:\\NIKKE\\MDA\\agent\\go-service\\taskersink\\membership\\memberdata.go", "source_location": "L315"}, {"id": "membership_memberdata_shorthash", "label": "shortHash()", "file_type": "code", "source_file": "D:\\NIKKE\\MDA\\agent\\go-service\\taskersink\\membership\\memberdata.go", "source_location": "L328"}], "edges": [{"source": "d_nikke_mda_agent_go_service_taskersink_membership_memberdata_go", "target": "go_pkg_encoding_json", "relation": "imports_from", "confidence": "EXTRACTED", "source_file": "D:\\NIKKE\\MDA\\agent\\go-service\\taskersink\\membership\\memberdata.go", "source_location": "L4", "weight": 1.0, "context": "import"}, {"source": "d_nikke_mda_agent_go_service_taskersink_membership_memberdata_go", "target": "go_pkg_fmt", "relation": "imports_from", "confidence": "EXTRACTED", "source_file": "D:\\NIKKE\\MDA\\agent\\go-service\\taskersink\\membership\\memberdata.go", "source_location": "L5", "weight": 1.0, "context": "import"}, {"source": "d_nikke_mda_agent_go_service_taskersink_membership_memberdata_go", "target": "go_pkg_io", "relation": "imports_from", "confidence": "EXTRACTED", "source_file": "D:\\NIKKE\\MDA\\agent\\go-service\\taskersink\\membership\\memberdata.go", "source_location": "L6", "weight": 1.0, "context": "import"}, {"source": "d_nikke_mda_agent_go_service_taskersink_membership_memberdata_go", "target": "go_pkg_math", "relation": "imports_from", "confidence": "EXTRACTED", "source_file": "D:\\NIKKE\\MDA\\agent\\go-service\\taskersink\\membership\\memberdata.go", "source_location": "L7", "weight": 1.0, "context": "import"}, {"source": "d_nikke_mda_agent_go_service_taskersink_membership_memberdata_go", "target": "go_pkg_net_http", "relation": "imports_from", "confidence": "EXTRACTED", "source_file": "D:\\NIKKE\\MDA\\agent\\go-service\\taskersink\\membership\\memberdata.go", "source_location": "L8", "weight": 1.0, "context": "import"}, {"source": "d_nikke_mda_agent_go_service_taskersink_membership_memberdata_go", "target": "go_pkg_strconv", "relation": "imports_from", "confidence": "EXTRACTED", "source_file": "D:\\NIKKE\\MDA\\agent\\go-service\\taskersink\\membership\\memberdata.go", "source_location": "L9", "weight": 1.0, "context": "import"}, {"source": "d_nikke_mda_agent_go_service_taskersink_membership_memberdata_go", "target": "go_pkg_strings", "relation": "imports_from", "confidence": "EXTRACTED", "source_file": "D:\\NIKKE\\MDA\\agent\\go-service\\taskersink\\membership\\memberdata.go", "source_location": "L10", "weight": 1.0, "context": "import"}, {"source": "d_nikke_mda_agent_go_service_taskersink_membership_memberdata_go", "target": "go_pkg_sync", "relation": "imports_from", "confidence": "EXTRACTED", "source_file": "D:\\NIKKE\\MDA\\agent\\go-service\\taskersink\\membership\\memberdata.go", "source_location": "L11", "weight": 1.0, "context": "import"}, {"source": "d_nikke_mda_agent_go_service_taskersink_membership_memberdata_go", "target": "go_pkg_time", "relation": "imports_from", "confidence": "EXTRACTED", "source_file": "D:\\NIKKE\\MDA\\agent\\go-service\\taskersink\\membership\\memberdata.go", "source_location": "L12", "weight": 1.0, "context": "import"}, {"source": "d_nikke_mda_agent_go_service_taskersink_membership_memberdata_go", "target": "go_pkg_github_com_rs_zerolog_log", "relation": "imports_from", "confidence": "EXTRACTED", "source_file": "D:\\NIKKE\\MDA\\agent\\go-service\\taskersink\\membership\\memberdata.go", "source_location": "L14", "weight": 1.0, "context": "import"}, {"source": "d_nikke_mda_agent_go_service_taskersink_membership_memberdata_go", "target": "membership_memberdata_setversion", "relation": "contains", "confidence": "EXTRACTED", "source_file": "D:\\NIKKE\\MDA\\agent\\go-service\\taskersink\\membership\\memberdata.go", "source_location": "L20", "weight": 1.0}, {"source": "d_nikke_mda_agent_go_service_taskersink_membership_memberdata_go", "target": "membership_memberdata_isdebugversion", "relation": "contains", "confidence": "EXTRACTED", "source_file": "D:\\NIKKE\\MDA\\agent\\go-service\\taskersink\\membership\\memberdata.go", "source_location": "L25", "weight": 1.0}, {"source": "d_nikke_mda_agent_go_service_taskersink_membership_memberdata_go", "target": "membership_memberrecord", "relation": "contains", "confidence": "EXTRACTED", "source_file": "D:\\NIKKE\\MDA\\agent\\go-service\\taskersink\\membership\\memberdata.go", "source_location": "L42", "weight": 1.0}, {"source": "d_nikke_mda_agent_go_service_taskersink_membership_memberdata_go", "target": "membership_membershipstatus", "relation": "contains", "confidence": "EXTRACTED", "source_file": "D:\\NIKKE\\MDA\\agent\\go-service\\taskersink\\membership\\memberdata.go", "source_location": "L56", "weight": 1.0}, {"source": "d_nikke_mda_agent_go_service_taskersink_membership_memberdata_go", "target": "membership_memberdata_getmembershipstatus", "relation": "contains", "confidence": "EXTRACTED", "source_file": "D:\\NIKKE\\MDA\\agent\\go-service\\taskersink\\membership\\memberdata.go", "source_location": "L83", "weight": 1.0}, {"source": "d_nikke_mda_agent_go_service_taskersink_membership_memberdata_go", "target": "membership_memberdata_checkmembership", "relation": "contains", "confidence": "EXTRACTED", "source_file": "D:\\NIKKE\\MDA\\agent\\go-service\\taskersink\\membership\\memberdata.go", "source_location": "L96", "weight": 1.0}, {"source": "d_nikke_mda_agent_go_service_taskersink_membership_memberdata_go", "target": "membership_memberdata_fetchmemberdata", "relation": "contains", "confidence": "EXTRACTED", "source_file": "D:\\NIKKE\\MDA\\agent\\go-service\\taskersink\\membership\\memberdata.go", "source_location": "L168", "weight": 1.0}, {"source": "d_nikke_mda_agent_go_service_taskersink_membership_memberdata_go", "target": "membership_memberdata_fetchfromsource", "relation": "contains", "confidence": "EXTRACTED", "source_file": "D:\\NIKKE\\MDA\\agent\\go-service\\taskersink\\membership\\memberdata.go", "source_location": "L193", "weight": 1.0}, {"source": "d_nikke_mda_agent_go_service_taskersink_membership_memberdata_go", "target": "membership_memberdata_matchdevicecode", "relation": "contains", "confidence": "EXTRACTED", "source_file": "D:\\NIKKE\\MDA\\agent\\go-service\\taskersink\\membership\\memberdata.go", "source_location": "L223", "weight": 1.0}, {"source": "d_nikke_mda_agent_go_service_taskersink_membership_memberdata_go", "target": "membership_memberdata_calculatestatus", "relation": "contains", "confidence": "EXTRACTED", "source_file": "D:\\NIKKE\\MDA\\agent\\go-service\\taskersink\\membership\\memberdata.go", "source_location": "L250", "weight": 1.0}, {"source": "d_nikke_mda_agent_go_service_taskersink_membership_memberdata_go", "target": "membership_memberdata_dayssince", "relation": "contains", "confidence": "EXTRACTED", "source_file": "D:\\NIKKE\\MDA\\agent\\go-service\\taskersink\\membership\\memberdata.go", "source_location": "L315", "weight": 1.0}, {"source": "d_nikke_mda_agent_go_service_taskersink_membership_memberdata_go", "target": "membership_memberdata_shorthash", "relation": "contains", "confidence": "EXTRACTED", "source_file": "D:\\NIKKE\\MDA\\agent\\go-service\\taskersink\\membership\\memberdata.go", "source_location": "L328", "weight": 1.0}, {"source": "membership_memberdata_getmembershipstatus", "target": "membership_memberdata_checkmembership", "relation": "calls", "context": "call", "confidence": "EXTRACTED", "source_file": "D:\\NIKKE\\MDA\\agent\\go-service\\taskersink\\membership\\memberdata.go", "source_location": "L92", "weight": 1.0}, {"source": "membership_memberdata_checkmembership", "target": "membership_memberdata_isdebugversion", "relation": "calls", "context": "call", "confidence": "EXTRACTED", "source_file": "D:\\NIKKE\\MDA\\agent\\go-service\\taskersink\\membership\\memberdata.go", "source_location": "L104", "weight": 1.0}, {"source": "membership_memberdata_checkmembership", "target": "membership_memberdata_shorthash", "relation": "calls", "context": "call", "confidence": "EXTRACTED", "source_file": "D:\\NIKKE\\MDA\\agent\\go-service\\taskersink\\membership\\memberdata.go", "source_location": "L120", "weight": 1.0}, {"source": "membership_memberdata_checkmembership", "target": "membership_memberdata_fetchmemberdata", "relation": "calls", "context": "call", "confidence": "EXTRACTED", "source_file": "D:\\NIKKE\\MDA\\agent\\go-service\\taskersink\\membership\\memberdata.go", "source_location": "L125", "weight": 1.0}, {"source": "membership_memberdata_checkmembership", "target": "membership_memberdata_matchdevicecode", "relation": "calls", "context": "call", "confidence": "EXTRACTED", "source_file": "D:\\NIKKE\\MDA\\agent\\go-service\\taskersink\\membership\\memberdata.go", "source_location": "L132", "weight": 1.0}, {"source": "membership_memberdata_checkmembership", "target": "membership_memberdata_calculatestatus", "relation": "calls", "context": "call", "confidence": "EXTRACTED", "source_file": "D:\\NIKKE\\MDA\\agent\\go-service\\taskersink\\membership\\memberdata.go", "source_location": "L154", "weight": 1.0}, {"source": "membership_memberdata_fetchmemberdata", "target": "membership_memberdata_fetchfromsource", "relation": "calls", "context": "call", "confidence": "EXTRACTED", "source_file": "D:\\NIKKE\\MDA\\agent\\go-service\\taskersink\\membership\\memberdata.go", "source_location": "L178", "weight": 1.0}, {"source": "membership_memberdata_calculatestatus", "target": "membership_memberdata_dayssince", "relation": "calls", "context": "call", "confidence": "EXTRACTED", "source_file": "D:\\NIKKE\\MDA\\agent\\go-service\\taskersink\\membership\\memberdata.go", "source_location": "L287", "weight": 1.0}], "raw_calls": [{"caller_nid": "membership_memberdata_isdebugversion", "callee": "TrimPrefix", "is_member_call": false, "source_file": "D:\\NIKKE\\MDA\\agent\\go-service\\taskersink\\membership\\memberdata.go", "source_location": "L29"}, {"caller_nid": "membership_memberdata_isdebugversion", "callee": "SplitN", "is_member_call": false, "source_file": "D:\\NIKKE\\MDA\\agent\\go-service\\taskersink\\membership\\memberdata.go", "source_location": "L30"}, {"caller_nid": "membership_memberdata_isdebugversion", "callee": "len", "is_member_call": false, "source_file": "D:\\NIKKE\\MDA\\agent\\go-service\\taskersink\\membership\\memberdata.go", "source_location": "L31"}, {"caller_nid": "membership_memberdata_isdebugversion", "callee": "Atoi", "is_member_call": false, "source_file": "D:\\NIKKE\\MDA\\agent\\go-service\\taskersink\\membership\\memberdata.go", "source_location": "L34"}, {"caller_nid": "membership_memberdata_getmembershipstatus", "callee": "RLock", "is_member_call": true, "source_file": "D:\\NIKKE\\MDA\\agent\\go-service\\taskersink\\membership\\memberdata.go", "source_location": "L84"}, {"caller_nid": "membership_memberdata_getmembershipstatus", "callee": "Since", "is_member_call": false, "source_file": "D:\\NIKKE\\MDA\\agent\\go-service\\taskersink\\membership\\memberdata.go", "source_location": "L85"}, {"caller_nid": "membership_memberdata_getmembershipstatus", "callee": "RUnlock", "is_member_call": true, "source_file": "D:\\NIKKE\\MDA\\agent\\go-service\\taskersink\\membership\\memberdata.go", "source_location": "L87"}, {"caller_nid": "membership_memberdata_getmembershipstatus", "callee": "RUnlock", "is_member_call": true, "source_file": "D:\\NIKKE\\MDA\\agent\\go-service\\taskersink\\membership\\memberdata.go", "source_location": "L90"}, {"caller_nid": "membership_memberdata_checkmembership", "callee": "Msg", "is_member_call": true, "source_file": "D:\\NIKKE\\MDA\\agent\\go-service\\taskersink\\membership\\memberdata.go", "source_location": "L105"}, {"caller_nid": "membership_memberdata_checkmembership", "callee": "Str", "is_member_call": true, "source_file": "D:\\NIKKE\\MDA\\agent\\go-service\\taskersink\\membership\\memberdata.go", "source_location": "L105"}, {"caller_nid": "membership_memberdata_checkmembership", "callee": "Info", "is_member_call": false, "source_file": "D:\\NIKKE\\MDA\\agent\\go-service\\taskersink\\membership\\memberdata.go", "source_location": "L105"}, {"caller_nid": "membership_memberdata_checkmembership", "callee": "GenerateDeviceCodeV6", "is_member_call": false, "source_file": "D:\\NIKKE\\MDA\\agent\\go-service\\taskersink\\membership\\memberdata.go", "source_location": "L115"}, {"caller_nid": "membership_memberdata_checkmembership", "callee": "Msg", "is_member_call": true, "source_file": "D:\\NIKKE\\MDA\\agent\\go-service\\taskersink\\membership\\memberdata.go", "source_location": "L119"}, {"caller_nid": "membership_memberdata_checkmembership", "callee": "Str", "is_member_call": true, "source_file": "D:\\NIKKE\\MDA\\agent\\go-service\\taskersink\\membership\\memberdata.go", "source_location": "L119"}, {"caller_nid": "membership_memberdata_checkmembership", "callee": "Str", "is_member_call": true, "source_file": "D:\\NIKKE\\MDA\\agent\\go-service\\taskersink\\membership\\memberdata.go", "source_location": "L119"}, {"caller_nid": "membership_memberdata_checkmembership", "callee": "Info", "is_member_call": false, "source_file": "D:\\NIKKE\\MDA\\agent\\go-service\\taskersink\\membership\\memberdata.go", "source_location": "L119"}, {"caller_nid": "membership_memberdata_checkmembership", "callee": "Msg", "is_member_call": true, "source_file": "D:\\NIKKE\\MDA\\agent\\go-service\\taskersink\\membership\\memberdata.go", "source_location": "L127"}, {"caller_nid": "membership_memberdata_checkmembership", "callee": "Err", "is_member_call": true, "source_file": "D:\\NIKKE\\MDA\\agent\\go-service\\taskersink\\membership\\memberdata.go", "source_location": "L127"}, {"caller_nid": "membership_memberdata_checkmembership", "callee": "Warn", "is_member_call": false, "source_file": "D:\\NIKKE\\MDA\\agent\\go-service\\taskersink\\membership\\memberdata.go", "source_location": "L127"}, {"caller_nid": "membership_memberdata_checkmembership", "callee": "Msg", "is_member_call": true, "source_file": "D:\\NIKKE\\MDA\\agent\\go-service\\taskersink\\membership\\memberdata.go", "source_location": "L134"}, {"caller_nid": "membership_memberdata_checkmembership", "callee": "Info", "is_member_call": false, "source_file": "D:\\NIKKE\\MDA\\agent\\go-service\\taskersink\\membership\\memberdata.go", "source_location": "L134"}, {"caller_nid": "membership_memberdata_checkmembership", "callee": "Msg", "is_member_call": true, "source_file": "D:\\NIKKE\\MDA\\agent\\go-service\\taskersink\\membership\\memberdata.go", "source_location": "L138"}, {"caller_nid": "membership_memberdata_checkmembership", "callee": "Str", "is_member_call": true, "source_file": "D:\\NIKKE\\MDA\\agent\\go-service\\taskersink\\membership\\memberdata.go", "source_location": "L138"}, {"caller_nid": "membership_memberdata_checkmembership", "callee": "Int", "is_member_call": true, "source_file": "D:\\NIKKE\\MDA\\agent\\go-service\\taskersink\\membership\\memberdata.go", "source_location": "L138"}, {"caller_nid": "membership_memberdata_checkmembership", "callee": "Str", "is_member_call": true, "source_file": "D:\\NIKKE\\MDA\\agent\\go-service\\taskersink\\membership\\memberdata.go", "source_location": "L138"}, {"caller_nid": "membership_memberdata_checkmembership", "callee": "Info", "is_member_call": false, "source_file": "D:\\NIKKE\\MDA\\agent\\go-service\\taskersink\\membership\\memberdata.go", "source_location": "L138"}, {"caller_nid": "membership_memberdata_checkmembership", "callee": "Msg", "is_member_call": true, "source_file": "D:\\NIKKE\\MDA\\agent\\go-service\\taskersink\\membership\\memberdata.go", "source_location": "L147"}, {"caller_nid": "membership_memberdata_checkmembership", "callee": "Str", "is_member_call": true, "source_file": "D:\\NIKKE\\MDA\\agent\\go-service\\taskersink\\membership\\memberdata.go", "source_location": "L147"}, {"caller_nid": "membership_memberdata_checkmembership", "callee": "Warn", "is_member_call": false, "source_file": "D:\\NIKKE\\MDA\\agent\\go-service\\taskersink\\membership\\memberdata.go", "source_location": "L147"}, {"caller_nid": "membership_memberdata_checkmembership", "callee": "Lock", "is_member_call": true, "source_file": "D:\\NIKKE\\MDA\\agent\\go-service\\taskersink\\membership\\memberdata.go", "source_location": "L159"}, {"caller_nid": "membership_memberdata_checkmembership", "callee": "Now", "is_member_call": false, "source_file": "D:\\NIKKE\\MDA\\agent\\go-service\\taskersink\\membership\\memberdata.go", "source_location": "L161"}, {"caller_nid": "membership_memberdata_checkmembership", "callee": "Unlock", "is_member_call": true, "source_file": "D:\\NIKKE\\MDA\\agent\\go-service\\taskersink\\membership\\memberdata.go", "source_location": "L162"}, {"caller_nid": "membership_memberdata_fetchmemberdata", "callee": "RLock", "is_member_call": true, "source_file": "D:\\NIKKE\\MDA\\agent\\go-service\\taskersink\\membership\\memberdata.go", "source_location": "L169"}, {"caller_nid": "membership_memberdata_fetchmemberdata", "callee": "Since", "is_member_call": false, "source_file": "D:\\NIKKE\\MDA\\agent\\go-service\\taskersink\\membership\\memberdata.go", "source_location": "L170"}, {"caller_nid": "membership_memberdata_fetchmemberdata", "callee": "RUnlock", "is_member_call": true, "source_file": "D:\\NIKKE\\MDA\\agent\\go-service\\taskersink\\membership\\memberdata.go", "source_location": "L172"}, {"caller_nid": "membership_memberdata_fetchmemberdata", "callee": "RUnlock", "is_member_call": true, "source_file": "D:\\NIKKE\\MDA\\agent\\go-service\\taskersink\\membership\\memberdata.go", "source_location": "L175"}, {"caller_nid": "membership_memberdata_fetchmemberdata", "callee": "Errorf", "is_member_call": false, "source_file": "D:\\NIKKE\\MDA\\agent\\go-service\\taskersink\\membership\\memberdata.go", "source_location": "L180"}, {"caller_nid": "membership_memberdata_fetchmemberdata", "callee": "Lock", "is_member_call": true, "source_file": "D:\\NIKKE\\MDA\\agent\\go-service\\taskersink\\membership\\memberdata.go", "source_location": "L183"}, {"caller_nid": "membership_memberdata_fetchmemberdata", "callee": "Now", "is_member_call": false, "source_file": "D:\\NIKKE\\MDA\\agent\\go-service\\taskersink\\membership\\memberdata.go", "source_location": "L185"}, {"caller_nid": "membership_memberdata_fetchmemberdata", "callee": "Unlock", "is_member_call": true, "source_file": "D:\\NIKKE\\MDA\\agent\\go-service\\taskersink\\membership\\memberdata.go", "source_location": "L186"}, {"caller_nid": "membership_memberdata_fetchmemberdata", "callee": "Msg", "is_member_call": true, "source_file": "D:\\NIKKE\\MDA\\agent\\go-service\\taskersink\\membership\\memberdata.go", "source_location": "L188"}, {"caller_nid": "membership_memberdata_fetchmemberdata", "callee": "Int", "is_member_call": true, "source_file": "D:\\NIKKE\\MDA\\agent\\go-service\\taskersink\\membership\\memberdata.go", "source_location": "L188"}, {"caller_nid": "membership_memberdata_fetchmemberdata", "callee": "Str", "is_member_call": true, "source_file": "D:\\NIKKE\\MDA\\agent\\go-service\\taskersink\\membership\\memberdata.go", "source_location": "L188"}, {"caller_nid": "membership_memberdata_fetchmemberdata", "callee": "Info", "is_member_call": false, "source_file": "D:\\NIKKE\\MDA\\agent\\go-service\\taskersink\\membership\\memberdata.go", "source_location": "L188"}, {"caller_nid": "membership_memberdata_fetchmemberdata", "callee": "len", "is_member_call": false, "source_file": "D:\\NIKKE\\MDA\\agent\\go-service\\taskersink\\membership\\memberdata.go", "source_location": "L188"}, {"caller_nid": "membership_memberdata_fetchfromsource", "callee": "NewRequest", "is_member_call": false, "source_file": "D:\\NIKKE\\MDA\\agent\\go-service\\taskersink\\membership\\memberdata.go", "source_location": "L194"}, {"caller_nid": "membership_memberdata_fetchfromsource", "callee": "Set", "is_member_call": true, "source_file": "D:\\NIKKE\\MDA\\agent\\go-service\\taskersink\\membership\\memberdata.go", "source_location": "L198"}, {"caller_nid": "membership_memberdata_fetchfromsource", "callee": "Do", "is_member_call": true, "source_file": "D:\\NIKKE\\MDA\\agent\\go-service\\taskersink\\membership\\memberdata.go", "source_location": "L199"}, {"caller_nid": "membership_memberdata_fetchfromsource", "callee": "Close", "is_member_call": true, "source_file": "D:\\NIKKE\\MDA\\agent\\go-service\\taskersink\\membership\\memberdata.go", "source_location": "L203"}, {"caller_nid": "membership_memberdata_fetchfromsource", "callee": "Errorf", "is_member_call": false, "source_file": "D:\\NIKKE\\MDA\\agent\\go-service\\taskersink\\membership\\memberdata.go", "source_location": "L206"}, {"caller_nid": "membership_memberdata_fetchfromsource", "callee": "ReadAll", "is_member_call": false, "source_file": "D:\\NIKKE\\MDA\\agent\\go-service\\taskersink\\membership\\memberdata.go", "source_location": "L209"}, {"caller_nid": "membership_memberdata_fetchfromsource", "callee": "Unmarshal", "is_member_call": false, "source_file": "D:\\NIKKE\\MDA\\agent\\go-service\\taskersink\\membership\\memberdata.go", "source_location": "L215"}, {"caller_nid": "membership_memberdata_fetchfromsource", "callee": "Errorf", "is_member_call": false, "source_file": "D:\\NIKKE\\MDA\\agent\\go-service\\taskersink\\membership\\memberdata.go", "source_location": "L216"}, {"caller_nid": "membership_memberdata_matchdevicecode", "callee": "MatchDeviceCodeV6", "is_member_call": false, "source_file": "D:\\NIKKE\\MDA\\agent\\go-service\\taskersink\\membership\\memberdata.go", "source_location": "L236"}, {"caller_nid": "membership_memberdata_calculatestatus", "callee": "Msg", "is_member_call": true, "source_file": "D:\\NIKKE\\MDA\\agent\\go-service\\taskersink\\membership\\memberdata.go", "source_location": "L261"}, {"caller_nid": "membership_memberdata_calculatestatus", "callee": "Str", "is_member_call": true, "source_file": "D:\\NIKKE\\MDA\\agent\\go-service\\taskersink\\membership\\memberdata.go", "source_location": "L261"}, {"caller_nid": "membership_memberdata_calculatestatus", "callee": "Warn", "is_member_call": false, "source_file": "D:\\NIKKE\\MDA\\agent\\go-service\\taskersink\\membership\\memberdata.go", "source_location": "L261"}, {"caller_nid": "membership_memberdata_calculatestatus", "callee": "Float64", "is_member_call": true, "source_file": "D:\\NIKKE\\MDA\\agent\\go-service\\taskersink\\membership\\memberdata.go", "source_location": "L265"}, {"caller_nid": "membership_memberdata_calculatestatus", "callee": "Msg", "is_member_call": true, "source_file": "D:\\NIKKE\\MDA\\agent\\go-service\\taskersink\\membership\\memberdata.go", "source_location": "L267"}, {"caller_nid": "membership_memberdata_calculatestatus", "callee": "Err", "is_member_call": true, "source_file": "D:\\NIKKE\\MDA\\agent\\go-service\\taskersink\\membership\\memberdata.go", "source_location": "L267"}, {"caller_nid": "membership_memberdata_calculatestatus", "callee": "Stringer", "is_member_call": true, "source_file": "D:\\NIKKE\\MDA\\agent\\go-service\\taskersink\\membership\\memberdata.go", "source_location": "L267"}, {"caller_nid": "membership_memberdata_calculatestatus", "callee": "Warn", "is_member_call": false, "source_file": "D:\\NIKKE\\MDA\\agent\\go-service\\taskersink\\membership\\memberdata.go", "source_location": "L267"}, {"caller_nid": "membership_memberdata_calculatestatus", "callee": "float64", "is_member_call": false, "source_file": "D:\\NIKKE\\MDA\\agent\\go-service\\taskersink\\membership\\memberdata.go", "source_location": "L292"}, {"caller_nid": "membership_memberdata_calculatestatus", "callee": "int", "is_member_call": false, "source_file": "D:\\NIKKE\\MDA\\agent\\go-service\\taskersink\\membership\\memberdata.go", "source_location": "L302"}, {"caller_nid": "membership_memberdata_calculatestatus", "callee": "Floor", "is_member_call": false, "source_file": "D:\\NIKKE\\MDA\\agent\\go-service\\taskersink\\membership\\memberdata.go", "source_location": "L302"}, {"caller_nid": "membership_memberdata_calculatestatus", "callee": "Format", "is_member_call": true, "source_file": "D:\\NIKKE\\MDA\\agent\\go-service\\taskersink\\membership\\memberdata.go", "source_location": "L303"}, {"caller_nid": "membership_memberdata_calculatestatus", "callee": "AddDate", "is_member_call": true, "source_file": "D:\\NIKKE\\MDA\\agent\\go-service\\taskersink\\membership\\memberdata.go", "source_location": "L303"}, {"caller_nid": "membership_memberdata_calculatestatus", "callee": "Now", "is_member_call": false, "source_file": "D:\\NIKKE\\MDA\\agent\\go-service\\taskersink\\membership\\memberdata.go", "source_location": "L303"}, {"caller_nid": "membership_memberdata_dayssince", "callee": "TrimSpace", "is_member_call": false, "source_file": "D:\\NIKKE\\MDA\\agent\\go-service\\taskersink\\membership\\memberdata.go", "source_location": "L316"}, {"caller_nid": "membership_memberdata_dayssince", "callee": "len", "is_member_call": false, "source_file": "D:\\NIKKE\\MDA\\agent\\go-service\\taskersink\\membership\\memberdata.go", "source_location": "L317"}, {"caller_nid": "membership_memberdata_dayssince", "callee": "ParseInLocation", "is_member_call": false, "source_file": "D:\\NIKKE\\MDA\\agent\\go-service\\taskersink\\membership\\memberdata.go", "source_location": "L320"}, {"caller_nid": "membership_memberdata_dayssince", "callee": "Msg", "is_member_call": true, "source_file": "D:\\NIKKE\\MDA\\agent\\go-service\\taskersink\\membership\\memberdata.go", "source_location": "L322"}, {"caller_nid": "membership_memberdata_dayssince", "callee": "Err", "is_member_call": true, "source_file": "D:\\NIKKE\\MDA\\agent\\go-service\\taskersink\\membership\\memberdata.go", "source_location": "L322"}, {"caller_nid": "membership_memberdata_dayssince", "callee": "Str", "is_member_call": true, "source_file": "D:\\NIKKE\\MDA\\agent\\go-service\\taskersink\\membership\\memberdata.go", "source_location": "L322"}, {"caller_nid": "membership_memberdata_dayssince", "callee": "Debug", "is_member_call": false, "source_file": "D:\\NIKKE\\MDA\\agent\\go-service\\taskersink\\membership\\memberdata.go", "source_location": "L322"}, {"caller_nid": "membership_memberdata_dayssince", "callee": "int", "is_member_call": false, "source_file": "D:\\NIKKE\\MDA\\agent\\go-service\\taskersink\\membership\\memberdata.go", "source_location": "L325"}, {"caller_nid": "membership_memberdata_dayssince", "callee": "Hours", "is_member_call": true, "source_file": "D:\\NIKKE\\MDA\\agent\\go-service\\taskersink\\membership\\memberdata.go", "source_location": "L325"}, {"caller_nid": "membership_memberdata_dayssince", "callee": "Since", "is_member_call": false, "source_file": "D:\\NIKKE\\MDA\\agent\\go-service\\taskersink\\membership\\memberdata.go", "source_location": "L325"}, {"caller_nid": "membership_memberdata_shorthash", "callee": "len", "is_member_call": false, "source_file": "D:\\NIKKE\\MDA\\agent\\go-service\\taskersink\\membership\\memberdata.go", "source_location": "L329"}]}