{"nodes": [{"id": "d_nikke_mda_agent_go_service_pkg_pienv_pienv_go", "label": "pienv.go", "file_type": "code", "source_file": "D:\\NIKKE\\MDA\\agent\\go-service\\pkg\\pienv\\pienv.go", "source_location": "L1"}, {"id": "pienv_win32config", "label": "Win32Config", "file_type": "code", "source_file": "D:\\NIKKE\\MDA\\agent\\go-service\\pkg\\pienv\\pienv.go", "source_location": "L24"}, {"id": "pienv_controller", "label": "Controller", "file_type": "code", "source_file": "D:\\NIKKE\\MDA\\agent\\go-service\\pkg\\pienv\\pienv.go", "source_location": "L33"}, {"id": "pienv_resource", "label": "Resource", "file_type": "code", "source_file": "D:\\NIKKE\\MDA\\agent\\go-service\\pkg\\pienv\\pienv.go", "source_location": "L50"}, {"id": "pienv_env", "label": "Env", "file_type": "code", "source_file": "D:\\NIKKE\\MDA\\agent\\go-service\\pkg\\pienv\\pienv.go", "source_location": "L61"}, {"id": "pienv_pienv_doinit", "label": "doInit()", "file_type": "code", "source_file": "D:\\NIKKE\\MDA\\agent\\go-service\\pkg\\pienv\\pienv.go", "source_location": "L80"}, {"id": "pienv_pienv_init", "label": "Init()", "file_type": "code", "source_file": "D:\\NIKKE\\MDA\\agent\\go-service\\pkg\\pienv\\pienv.go", "source_location": "L140"}, {"id": "pienv_pienv_get", "label": "Get()", "file_type": "code", "source_file": "D:\\NIKKE\\MDA\\agent\\go-service\\pkg\\pienv\\pienv.go", "source_location": "L145"}, {"id": "pienv_pienv_interfaceversion", "label": "InterfaceVersion()", "file_type": "code", "source_file": "D:\\NIKKE\\MDA\\agent\\go-service\\pkg\\pienv\\pienv.go", "source_location": "L153"}, {"id": "pienv_pienv_clientname", "label": "ClientName()", "file_type": "code", "source_file": "D:\\NIKKE\\MDA\\agent\\go-service\\pkg\\pienv\\pienv.go", "source_location": "L156"}, {"id": "pienv_pienv_clientversion", "label": "ClientVersion()", "file_type": "code", "source_file": "D:\\NIKKE\\MDA\\agent\\go-service\\pkg\\pienv\\pienv.go", "source_location": "L159"}, {"id": "pienv_pienv_clientlanguage", "label": "ClientLanguage()", "file_type": "code", "source_file": "D:\\NIKKE\\MDA\\agent\\go-service\\pkg\\pienv\\pienv.go", "source_location": "L162"}, {"id": "pienv_pienv_clientmaafwversion", "label": "ClientMaaFWVersion()", "file_type": "code", "source_file": "D:\\NIKKE\\MDA\\agent\\go-service\\pkg\\pienv\\pienv.go", "source_location": "L165"}, {"id": "pienv_pienv_projectversion", "label": "ProjectVersion()", "file_type": "code", "source_file": "D:\\NIKKE\\MDA\\agent\\go-service\\pkg\\pienv\\pienv.go", "source_location": "L168"}, {"id": "pienv_pienv_getcontroller", "label": "GetController()", "file_type": "code", "source_file": "D:\\NIKKE\\MDA\\agent\\go-service\\pkg\\pienv\\pienv.go", "source_location": "L171"}, {"id": "pienv_pienv_getresource", "label": "GetResource()", "file_type": "code", "source_file": "D:\\NIKKE\\MDA\\agent\\go-service\\pkg\\pienv\\pienv.go", "source_location": "L174"}, {"id": "pienv_pienv_controllertype", "label": "ControllerType()", "file_type": "code", "source_file": "D:\\NIKKE\\MDA\\agent\\go-service\\pkg\\pienv\\pienv.go", "source_location": "L177"}, {"id": "pienv_pienv_controllername", "label": "ControllerName()", "file_type": "code", "source_file": "D:\\NIKKE\\MDA\\agent\\go-service\\pkg\\pienv\\pienv.go", "source_location": "L185"}, {"id": "pienv_pienv_resourcename", "label": "ResourceName()", "file_type": "code", "source_file": "D:\\NIKKE\\MDA\\agent\\go-service\\pkg\\pienv\\pienv.go", "source_location": "L193"}], "edges": [{"source": "d_nikke_mda_agent_go_service_pkg_pienv_pienv_go", "target": "go_pkg_encoding_json", "relation": "imports_from", "confidence": "EXTRACTED", "source_file": "D:\\NIKKE\\MDA\\agent\\go-service\\pkg\\pienv\\pienv.go", "source_location": "L4", "weight": 1.0, "context": "import"}, {"source": "d_nikke_mda_agent_go_service_pkg_pienv_pienv_go", "target": "go_pkg_os", "relation": "imports_from", "confidence": "EXTRACTED", "source_file": "D:\\NIKKE\\MDA\\agent\\go-service\\pkg\\pienv\\pienv.go", "source_location": "L5", "weight": 1.0, "context": "import"}, {"source": "d_nikke_mda_agent_go_service_pkg_pienv_pienv_go", "target": "go_pkg_sync", "relation": "imports_from", "confidence": "EXTRACTED", "source_file": "D:\\NIKKE\\MDA\\agent\\go-service\\pkg\\pienv\\pienv.go", "source_location": "L6", "weight": 1.0, "context": "import"}, {"source": "d_nikke_mda_agent_go_service_pkg_pienv_pienv_go", "target": "go_pkg_github_com_rs_zerolog_log", "relation": "imports_from", "confidence": "EXTRACTED", "source_file": "D:\\NIKKE\\MDA\\agent\\go-service\\pkg\\pienv\\pienv.go", "source_location": "L8", "weight": 1.0, "context": "import"}, {"source": "d_nikke_mda_agent_go_service_pkg_pienv_pienv_go", "target": "pienv_win32config", "relation": "contains", "confidence": "EXTRACTED", "source_file": "D:\\NIKKE\\MDA\\agent\\go-service\\pkg\\pienv\\pienv.go", "source_location": "L24", "weight": 1.0}, {"source": "d_nikke_mda_agent_go_service_pkg_pienv_pienv_go", "target": "pienv_controller", "relation": "contains", "confidence": "EXTRACTED", "source_file": "D:\\NIKKE\\MDA\\agent\\go-service\\pkg\\pienv\\pienv.go", "source_location": "L33", "weight": 1.0}, {"source": "d_nikke_mda_agent_go_service_pkg_pienv_pienv_go", "target": "pienv_resource", "relation": "contains", "confidence": "EXTRACTED", "source_file": "D:\\NIKKE\\MDA\\agent\\go-service\\pkg\\pienv\\pienv.go", "source_location": "L50", "weight": 1.0}, {"source": "d_nikke_mda_agent_go_service_pkg_pienv_pienv_go", "target": "pienv_env", "relation": "contains", "confidence": "EXTRACTED", "source_file": "D:\\NIKKE\\MDA\\agent\\go-service\\pkg\\pienv\\pienv.go", "source_location": "L61", "weight": 1.0}, {"source": "d_nikke_mda_agent_go_service_pkg_pienv_pienv_go", "target": "pienv_pienv_doinit", "relation": "contains", "confidence": "EXTRACTED", "source_file": "D:\\NIKKE\\MDA\\agent\\go-service\\pkg\\pienv\\pienv.go", "source_location": "L80", "weight": 1.0}, {"source": "d_nikke_mda_agent_go_service_pkg_pienv_pienv_go", "target": "pienv_pienv_init", "relation": "contains", "confidence": "EXTRACTED", "source_file": "D:\\NIKKE\\MDA\\agent\\go-service\\pkg\\pienv\\pienv.go", "source_location": "L140", "weight": 1.0}, {"source": "d_nikke_mda_agent_go_service_pkg_pienv_pienv_go", "target": "pienv_pienv_get", "relation": "contains", "confidence": "EXTRACTED", "source_file": "D:\\NIKKE\\MDA\\agent\\go-service\\pkg\\pienv\\pienv.go", "source_location": "L145", "weight": 1.0}, {"source": "d_nikke_mda_agent_go_service_pkg_pienv_pienv_go", "target": "pienv_pienv_interfaceversion", "relation": "contains", "confidence": "EXTRACTED", "source_file": "D:\\NIKKE\\MDA\\agent\\go-service\\pkg\\pienv\\pienv.go", "source_location": "L153", "weight": 1.0}, {"source": "d_nikke_mda_agent_go_service_pkg_pienv_pienv_go", "target": "pienv_pienv_clientname", "relation": "contains", "confidence": "EXTRACTED", "source_file": "D:\\NIKKE\\MDA\\agent\\go-service\\pkg\\pienv\\pienv.go", "source_location": "L156", "weight": 1.0}, {"source": "d_nikke_mda_agent_go_service_pkg_pienv_pienv_go", "target": "pienv_pienv_clientversion", "relation": "contains", "confidence": "EXTRACTED", "source_file": "D:\\NIKKE\\MDA\\agent\\go-service\\pkg\\pienv\\pienv.go", "source_location": "L159", "weight": 1.0}, {"source": "d_nikke_mda_agent_go_service_pkg_pienv_pienv_go", "target": "pienv_pienv_clientlanguage", "relation": "contains", "confidence": "EXTRACTED", "source_file": "D:\\NIKKE\\MDA\\agent\\go-service\\pkg\\pienv\\pienv.go", "source_location": "L162", "weight": 1.0}, {"source": "d_nikke_mda_agent_go_service_pkg_pienv_pienv_go", "target": "pienv_pienv_clientmaafwversion", "relation": "contains", "confidence": "EXTRACTED", "source_file": "D:\\NIKKE\\MDA\\agent\\go-service\\pkg\\pienv\\pienv.go", "source_location": "L165", "weight": 1.0}, {"source": "d_nikke_mda_agent_go_service_pkg_pienv_pienv_go", "target": "pienv_pienv_projectversion", "relation": "contains", "confidence": "EXTRACTED", "source_file": "D:\\NIKKE\\MDA\\agent\\go-service\\pkg\\pienv\\pienv.go", "source_location": "L168", "weight": 1.0}, {"source": "d_nikke_mda_agent_go_service_pkg_pienv_pienv_go", "target": "pienv_pienv_getcontroller", "relation": "contains", "confidence": "EXTRACTED", "source_file": "D:\\NIKKE\\MDA\\agent\\go-service\\pkg\\pienv\\pienv.go", "source_location": "L171", "weight": 1.0}, {"source": "d_nikke_mda_agent_go_service_pkg_pienv_pienv_go", "target": "pienv_pienv_getresource", "relation": "contains", "confidence": "EXTRACTED", "source_file": "D:\\NIKKE\\MDA\\agent\\go-service\\pkg\\pienv\\pienv.go", "source_location": "L174", "weight": 1.0}, {"source": "d_nikke_mda_agent_go_service_pkg_pienv_pienv_go", "target": "pienv_pienv_controllertype", "relation": "contains", "confidence": "EXTRACTED", "source_file": "D:\\NIKKE\\MDA\\agent\\go-service\\pkg\\pienv\\pienv.go", "source_location": "L177", "weight": 1.0}, {"source": "d_nikke_mda_agent_go_service_pkg_pienv_pienv_go", "target": "pienv_pienv_controllername", "relation": "contains", "confidence": "EXTRACTED", "source_file": "D:\\NIKKE\\MDA\\agent\\go-service\\pkg\\pienv\\pienv.go", "source_location": "L185", "weight": 1.0}, {"source": "d_nikke_mda_agent_go_service_pkg_pienv_pienv_go", "target": "pienv_pienv_resourcename", "relation": "contains", "confidence": "EXTRACTED", "source_file": "D:\\NIKKE\\MDA\\agent\\go-service\\pkg\\pienv\\pienv.go", "source_location": "L193", "weight": 1.0}, {"source": "pienv_pienv_interfaceversion", "target": "pienv_pienv_get", "relation": "calls", "context": "call", "confidence": "EXTRACTED", "source_file": "D:\\NIKKE\\MDA\\agent\\go-service\\pkg\\pienv\\pienv.go", "source_location": "L153", "weight": 1.0}, {"source": "pienv_pienv_clientname", "target": "pienv_pienv_get", "relation": "calls", "context": "call", "confidence": "EXTRACTED", "source_file": "D:\\NIKKE\\MDA\\agent\\go-service\\pkg\\pienv\\pienv.go", "source_location": "L156", "weight": 1.0}, {"source": "pienv_pienv_clientversion", "target": "pienv_pienv_get", "relation": "calls", "context": "call", "confidence": "EXTRACTED", "source_file": "D:\\NIKKE\\MDA\\agent\\go-service\\pkg\\pienv\\pienv.go", "source_location": "L159", "weight": 1.0}, {"source": "pienv_pienv_clientlanguage", "target": "pienv_pienv_get", "relation": "calls", "context": "call", "confidence": "EXTRACTED", "source_file": "D:\\NIKKE\\MDA\\agent\\go-service\\pkg\\pienv\\pienv.go", "source_location": "L162", "weight": 1.0}, {"source": "pienv_pienv_clientmaafwversion", "target": "pienv_pienv_get", "relation": "calls", "context": "call", "confidence": "EXTRACTED", "source_file": "D:\\NIKKE\\MDA\\agent\\go-service\\pkg\\pienv\\pienv.go", "source_location": "L165", "weight": 1.0}, {"source": "pienv_pienv_projectversion", "target": "pienv_pienv_get", "relation": "calls", "context": "call", "confidence": "EXTRACTED", "source_file": "D:\\NIKKE\\MDA\\agent\\go-service\\pkg\\pienv\\pienv.go", "source_location": "L168", "weight": 1.0}, {"source": "pienv_pienv_getcontroller", "target": "pienv_pienv_get", "relation": "calls", "context": "call", "confidence": "EXTRACTED", "source_file": "D:\\NIKKE\\MDA\\agent\\go-service\\pkg\\pienv\\pienv.go", "source_location": "L171", "weight": 1.0}, {"source": "pienv_pienv_getresource", "target": "pienv_pienv_get", "relation": "calls", "context": "call", "confidence": "EXTRACTED", "source_file": "D:\\NIKKE\\MDA\\agent\\go-service\\pkg\\pienv\\pienv.go", "source_location": "L174", "weight": 1.0}, {"source": "pienv_pienv_controllertype", "target": "pienv_pienv_getcontroller", "relation": "calls", "context": "call", "confidence": "EXTRACTED", "source_file": "D:\\NIKKE\\MDA\\agent\\go-service\\pkg\\pienv\\pienv.go", "source_location": "L178", "weight": 1.0}, {"source": "pienv_pienv_controllername", "target": "pienv_pienv_getcontroller", "relation": "calls", "context": "call", "confidence": "EXTRACTED", "source_file": "D:\\NIKKE\\MDA\\agent\\go-service\\pkg\\pienv\\pienv.go", "source_location": "L186", "weight": 1.0}, {"source": "pienv_pienv_resourcename", "target": "pienv_pienv_getresource", "relation": "calls", "context": "call", "confidence": "EXTRACTED", "source_file": "D:\\NIKKE\\MDA\\agent\\go-service\\pkg\\pienv\\pienv.go", "source_location": "L194", "weight": 1.0}], "raw_calls": [{"caller_nid": "pienv_pienv_doinit", "callee": "Getenv", "is_member_call": false, "source_file": "D:\\NIKKE\\MDA\\agent\\go-service\\pkg\\pienv\\pienv.go", "source_location": "L82"}, {"caller_nid": "pienv_pienv_doinit", "callee": "Getenv", "is_member_call": false, "source_file": "D:\\NIKKE\\MDA\\agent\\go-service\\pkg\\pienv\\pienv.go", "source_location": "L83"}, {"caller_nid": "pienv_pienv_doinit", "callee": "Getenv", "is_member_call": false, "source_file": "D:\\NIKKE\\MDA\\agent\\go-service\\pkg\\pienv\\pienv.go", "source_location": "L84"}, {"caller_nid": "pienv_pienv_doinit", "callee": "Getenv", "is_member_call": false, "source_file": "D:\\NIKKE\\MDA\\agent\\go-service\\pkg\\pienv\\pienv.go", "source_location": "L85"}, {"caller_nid": "pienv_pienv_doinit", "callee": "Getenv", "is_member_call": false, "source_file": "D:\\NIKKE\\MDA\\agent\\go-service\\pkg\\pienv\\pienv.go", "source_location": "L86"}, {"caller_nid": "pienv_pienv_doinit", "callee": "Getenv", "is_member_call": false, "source_file": "D:\\NIKKE\\MDA\\agent\\go-service\\pkg\\pienv\\pienv.go", "source_location": "L87"}, {"caller_nid": "pienv_pienv_doinit", "callee": "Getenv", "is_member_call": false, "source_file": "D:\\NIKKE\\MDA\\agent\\go-service\\pkg\\pienv\\pienv.go", "source_location": "L88"}, {"caller_nid": "pienv_pienv_doinit", "callee": "Getenv", "is_member_call": false, "source_file": "D:\\NIKKE\\MDA\\agent\\go-service\\pkg\\pienv\\pienv.go", "source_location": "L89"}, {"caller_nid": "pienv_pienv_doinit", "callee": "Unmarshal", "is_member_call": false, "source_file": "D:\\NIKKE\\MDA\\agent\\go-service\\pkg\\pienv\\pienv.go", "source_location": "L94"}, {"caller_nid": "pienv_pienv_doinit", "callee": "Msg", "is_member_call": true, "source_file": "D:\\NIKKE\\MDA\\agent\\go-service\\pkg\\pienv\\pienv.go", "source_location": "L95"}, {"caller_nid": "pienv_pienv_doinit", "callee": "Str", "is_member_call": true, "source_file": "D:\\NIKKE\\MDA\\agent\\go-service\\pkg\\pienv\\pienv.go", "source_location": "L95"}, {"caller_nid": "pienv_pienv_doinit", "callee": "Str", "is_member_call": true, "source_file": "D:\\NIKKE\\MDA\\agent\\go-service\\pkg\\pienv\\pienv.go", "source_location": "L95"}, {"caller_nid": "pienv_pienv_doinit", "callee": "Err", "is_member_call": true, "source_file": "D:\\NIKKE\\MDA\\agent\\go-service\\pkg\\pienv\\pienv.go", "source_location": "L95"}, {"caller_nid": "pienv_pienv_doinit", "callee": "Warn", "is_member_call": false, "source_file": "D:\\NIKKE\\MDA\\agent\\go-service\\pkg\\pienv\\pienv.go", "source_location": "L95"}, {"caller_nid": "pienv_pienv_doinit", "callee": "Unmarshal", "is_member_call": false, "source_file": "D:\\NIKKE\\MDA\\agent\\go-service\\pkg\\pienv\\pienv.go", "source_location": "L106"}, {"caller_nid": "pienv_pienv_doinit", "callee": "Msg", "is_member_call": true, "source_file": "D:\\NIKKE\\MDA\\agent\\go-service\\pkg\\pienv\\pienv.go", "source_location": "L107"}, {"caller_nid": "pienv_pienv_doinit", "callee": "Str", "is_member_call": true, "source_file": "D:\\NIKKE\\MDA\\agent\\go-service\\pkg\\pienv\\pienv.go", "source_location": "L107"}, {"caller_nid": "pienv_pienv_doinit", "callee": "Str", "is_member_call": true, "source_file": "D:\\NIKKE\\MDA\\agent\\go-service\\pkg\\pienv\\pienv.go", "source_location": "L107"}, {"caller_nid": "pienv_pienv_doinit", "callee": "Err", "is_member_call": true, "source_file": "D:\\NIKKE\\MDA\\agent\\go-service\\pkg\\pienv\\pienv.go", "source_location": "L107"}, {"caller_nid": "pienv_pienv_doinit", "callee": "Warn", "is_member_call": false, "source_file": "D:\\NIKKE\\MDA\\agent\\go-service\\pkg\\pienv\\pienv.go", "source_location": "L107"}, {"caller_nid": "pienv_pienv_doinit", "callee": "Bool", "is_member_call": true, "source_file": "D:\\NIKKE\\MDA\\agent\\go-service\\pkg\\pienv\\pienv.go", "source_location": "L118"}, {"caller_nid": "pienv_pienv_doinit", "callee": "Bool", "is_member_call": true, "source_file": "D:\\NIKKE\\MDA\\agent\\go-service\\pkg\\pienv\\pienv.go", "source_location": "L118"}, {"caller_nid": "pienv_pienv_doinit", "callee": "Str", "is_member_call": true, "source_file": "D:\\NIKKE\\MDA\\agent\\go-service\\pkg\\pienv\\pienv.go", "source_location": "L118"}, {"caller_nid": "pienv_pienv_doinit", "callee": "Str", "is_member_call": true, "source_file": "D:\\NIKKE\\MDA\\agent\\go-service\\pkg\\pienv\\pienv.go", "source_location": "L118"}, {"caller_nid": "pienv_pienv_doinit", "callee": "Str", "is_member_call": true, "source_file": "D:\\NIKKE\\MDA\\agent\\go-service\\pkg\\pienv\\pienv.go", "source_location": "L118"}, {"caller_nid": "pienv_pienv_doinit", "callee": "Str", "is_member_call": true, "source_file": "D:\\NIKKE\\MDA\\agent\\go-service\\pkg\\pienv\\pienv.go", "source_location": "L118"}, {"caller_nid": "pienv_pienv_doinit", "callee": "Str", "is_member_call": true, "source_file": "D:\\NIKKE\\MDA\\agent\\go-service\\pkg\\pienv\\pienv.go", "source_location": "L118"}, {"caller_nid": "pienv_pienv_doinit", "callee": "Str", "is_member_call": true, "source_file": "D:\\NIKKE\\MDA\\agent\\go-service\\pkg\\pienv\\pienv.go", "source_location": "L118"}, {"caller_nid": "pienv_pienv_doinit", "callee": "Info", "is_member_call": false, "source_file": "D:\\NIKKE\\MDA\\agent\\go-service\\pkg\\pienv\\pienv.go", "source_location": "L118"}, {"caller_nid": "pienv_pienv_doinit", "callee": "Str", "is_member_call": true, "source_file": "D:\\NIKKE\\MDA\\agent\\go-service\\pkg\\pienv\\pienv.go", "source_location": "L129"}, {"caller_nid": "pienv_pienv_doinit", "callee": "Str", "is_member_call": true, "source_file": "D:\\NIKKE\\MDA\\agent\\go-service\\pkg\\pienv\\pienv.go", "source_location": "L129"}, {"caller_nid": "pienv_pienv_doinit", "callee": "Str", "is_member_call": true, "source_file": "D:\\NIKKE\\MDA\\agent\\go-service\\pkg\\pienv\\pienv.go", "source_location": "L133"}, {"caller_nid": "pienv_pienv_doinit", "callee": "Msg", "is_member_call": true, "source_file": "D:\\NIKKE\\MDA\\agent\\go-service\\pkg\\pienv\\pienv.go", "source_location": "L136"}, {"caller_nid": "pienv_pienv_init", "callee": "Do", "is_member_call": true, "source_file": "D:\\NIKKE\\MDA\\agent\\go-service\\pkg\\pienv\\pienv.go", "source_location": "L141"}, {"caller_nid": "pienv_pienv_get", "callee": "Do", "is_member_call": true, "source_file": "D:\\NIKKE\\MDA\\agent\\go-service\\pkg\\pienv\\pienv.go", "source_location": "L146"}]}